[
  {
    "username": "user1",
    "password": "abc@123",
    "firstname": "mahesh",
    "lastname": "patel"
  },
  {
    "username": "user2",
    "password": "abc@123",
    "firstname": "ramesh",
    "lastname": "choudhary"
  },
  {
    "username": "user3",
    "password": "abc@123",
    "firstname": "max",
    "lastname": "greg"
  },
  {
    "username": "shivam",
    "password": "asdf@123",
    "firstname": "shivam",
    "lastname": "gupta",
    "Created_on": 1618397877719
  },
  {
    "username": "user5",
    "password": "password",
    "firstname": "raj",
    "lastname": "kumar",
    "Created_on": 1618398028579
  }
]